{"_id":"f9bdfd1e-6968-4631-9f2a-b303b01bf529","_type":"location","sw_id":"PG002027_2_1_0","address_id":"f7d914c0-12cc-41a7-a5b2-2b3f4526e063","organization_id":"c2732118-f444-49c2-aa3f-7d6d4e7e5b4b","short_desc":"Offers four levels of living for senior citizens, residential, assisted, memory support and skilled nursing care","description":"At Piedmont Gardens, a senior living community that’s as active and unique inside as it is outside. As the only continuing care retirement community in Oakland, Piedmont Gardens offers all levels of long-term senior care to go along with an exciting array of retirement services. So it’s easy to stay connected to everything you need to keep living the flavorful senior living lifestyle you want."}