{"_id":"1be84ff0-0b7e-460b-8e8e-04f360a38e3d","_type":"location","sw_id":"PG000781_2_1_0","address_id":"71fe4154-a01a-456d-80db-079acaa702b3","organization_id":"d00354a9-1ebe-48a9-9b18-938ba90fe0ff","short_desc":"Clinical assessment, individual, family and school-based counseling, day and residential treatment for special education children and youth, age 6-21","description":"Provides assessment and certification for special education children and youth up to age 22, to establish eligibility for educationally - related mental health services in Alameda County. Services provided to eligible children and youth include clinical assessment, outpatient individual and family therapy, school-based counseling, day treatment, residential treatment and case management. A referral from the school district is required to apply for service."}