{"_id":"34f2d3a5-010c-462e-9847-5f57851852e8","_type":"location","sw_id":"PG001809_2_1_0","name":"Drop-In Center","address_id":"5e192d53-bb4d-4b26-8c40-2b8a4996d307","organization_id":"47454cd2-7c2c-4e3d-a36f-dbc2725680fd","short_desc":"Works in partnership with the AIDS Project of the East Bay to help stop the spread of HIV/AIDS and Hepatitis C","description":"WALK-IN (NO APPOINTMENT NECESSARY): HIV testing and Hepatitis C testing, Pregnancy testing, free condoms, and access to shower, laundry and food bags.STD CLINIC open Monday, 12-4; Tuesday -Thursday, 10-4; Friday, 10-3; Testing, counseling, treatment and referrals for Chlamydia, Gonorrhea, Herpes, Syphilis, Hepatitis B and C, Human Papilloma Virus (HPV) and Trichomoniasis.  ABSCESS AND WOUND CARE CLINIC open Monday, 12-4; Tuesday-Thursday, 10-4; Friday, 10-3; Provides care for abscesses and other wounds that can result from injection drug use."}