{"_id":"d2318816-b859-43c6-b740-5e10a174ee16","_type":"location","sw_id":"PG004332_2_1_0","name":"Buy Back","address_id":"88b27881-7a8c-4fa9-ad81-806e8434ddfb","organization_id":"d247c220-6fa2-4796-b7ea-3ec3767a1d04","short_desc":"Provides a site to get paid for recycling materials","description":"Pays for selected recyclables by weight or count.Located at 2nd Street and Gilman, and is open Tuesday through Sunday, 9-4. Materials should be sorted before arrival at the Buyback Center. Check \"Materials Preparation\" page on website for details."}