{"_id":"ce173749-b905-42ff-84ca-6e308eca8045","_type":"location","sw_id":"PG004143_2_1_0","address_id":"dd838b10-a305-4d7f-a865-341a0f03142d","organization_id":"2a909956-17a1-49fe-9aa2-8a32f60cf222","short_desc":"9-week Food Service training focuses on culinary, barista and customer service skills for jobs in food service","description":"Offers 9-week training that focuses on basic culinary, barista and customer service skills for jobs in cafés, restaurants and other food retail businesses. In addition, there is a strong job readiness component that includes resume writing, job search, interviewing, and other skills needed to transition into the food industry. TRAINEE REQUIREMENTS: Must love to cook and bake, be 18 years of age and older, low income, eligible to work in the U.S. or is in the process of getting a work permit, committed to finding a job in the food industry upon graduation, physically able to complete training, for example work on feet for 8 hours a day and lift 25 pounds, drug and alcohol free, free of violent or weapon-related offenses, able to read recipes in English, willing to receive follow-up calls from program staff after graduation.For application information call and have a pen and paper 888-283-3522."}