{"_id":"0aa87424-83bd-44d0-b5ac-270535b898eb","_type":"location","sw_id":"PG004339_2_1_0","address_id":"32042494-a9ca-42b1-89de-f2f476e87088","organization_id":"3f7215f3-bb88-40a6-a1b0-11df1a2734c7","short_desc":"FAFSA provides free application process for one of the Title IV Federal Student Aid programs of the U.S. Department of Education. Includes federal student aid grant, loan, and work-study programs","description":"Provides application process for one of the Title IV Federal Student Aid programs of the U.S. Department of Education.FEDERAL STUDENT AID GRANTS include: Federal Pell Grants, Federal Supplemental Educational Opportunity Grants (FSEOG), Academic Competitiveness Grants (ACG), National Science and Mathematics Access to Retain Talent (National SMART), Teacher Education Assistance for College and Higher Education Grants (TEACH), and Leveraging Educational Assistance Partnership (LEAP) and Special LEAP Grants.FEDERAL STUDENT AID LOANS include: Direct Loan Program (Stafford, PLUS and Consolitation loans), Federal Perkins Loans.FEDERAL STUDENT AID WORK-STUDY: Work-Study programs.For application assistance, the Federal Student Aid Information Center can be contacted in the following ways: FAFSA On The Web - \"Live Help\" (secure online chat session with FAFSA customer service representative), by phone or by e-mail."}